Metadata-Version: 1.1
Name: pylangtools
Version: 0.0.2
Summary: 繁体简体转换
Home-page: UNKNOWN
Author: Rosefun
Author-email: rosefun@foxmail.com
License: UNKNOWN
Platform: UNKNOWN
Classifier: Programming Language :: Python :: 3
Classifier: License :: OSI Approved :: MIT License
Classifier: Operating System :: OS Independent
